orpc_server/__init__.py
orpc_server/cli.py
orpc_server/server.py
orpc_server/services.py
orpc_server-0.5.13.dist-info/licenses/LICENSE
orpc_server-0.5.13.dist-info/METADATA
orpc_server-0.5.13.dist-info/WHEEL
orpc_server-0.5.13.dist-info/entry_points.txt
orpc_server-0.5.13.dist-info/top_level.txt
orpc_server-0.5.13.dist-info/RECORD
