Metadata-Version: 2.4
Name: orpc-server
Version: 0.5.13
Summary: Open RPC server.
Author: rRR0VrFP
Maintainer: rRR0VrFP
License: MIT
Keywords: orpc,open rpc
Classifier: Development Status :: 5 - Production/Stable
Classifier: Intended Audience :: Developers
Classifier: Topic :: Software Development :: Libraries :: Python Modules
Classifier: License :: OSI Approved :: MIT License
Classifier: Programming Language :: Python :: 3
Classifier: Programming Language :: Python :: 3 :: Only
License-File: LICENSE
Requires-Dist: zenutils>=0.4.8
Requires-Dist: orpc-client>=0.5.10
Requires-Dist: daemon-application
Requires-Dist: bizerror
Dynamic: author
Dynamic: classifier
Dynamic: description
Dynamic: description-content-type
Dynamic: keywords
Dynamic: license
Dynamic: license-file
Dynamic: maintainer
Dynamic: requires-dist
Dynamic: summary
